LICENSE
MANIFEST.in
README.md
README.rst
setup.py
maxjoshua/__init__.py
maxjoshua/binsel.py
maxjoshua/bootcorr.py
maxjoshua/bootstrap_solutions.py
maxjoshua/enumerate_negations.py
maxjoshua/fltsel.py
maxjoshua/hard_voting.py
maxjoshua/negate_bool_features.py
maxjoshua/sparsenn.py
maxjoshua.egg-info/PKG-INFO
maxjoshua.egg-info/SOURCES.txt
maxjoshua.egg-info/dependency_links.txt
maxjoshua.egg-info/requires.txt
maxjoshua.egg-info/top_level.txt
maxjoshua.egg-info/zip-safe
test/__init__.py
test/test_binsel.py
test/test_bootcorr.py
test/test_bootstrap_solution.py
test/test_hard_voting.py
test/test_negate_bool_features.py