Metadata-Version: 2.1
Name: maxjoshua
Version: 0.4.3
Summary: Feature selection for hard voting classifier and NN sparse weight initialization.
Home-page: http://github.com/ulf1/maxjoshua
Author: Ulf Hamster
Author-email: 554c46@gmail.com
License: Apache License 2.0
Requires-Python: >=3.7
License-File: LICENSE
